porper/__init__.py
porper/controllers/__init__.py
porper/controllers/auth_controller.py
porper/controllers/github_auth_controller.py
porper/controllers/google_auth_controller.py
porper/controllers/group_controller.py
porper/controllers/invited_user_controller.py
porper/controllers/kms_controller.py
porper/controllers/permission_controller.py
porper/controllers/resource_controller.py
porper/controllers/slack_auth_controller.py
porper/controllers/sso_auth_controller.py
porper/controllers/token_controller.py
porper/controllers/user_controller.py
porper/controllers/user_group_controller.py
porper/models/__init__.py
porper/models/access_token.py
porper/models/decimal_encoder.py
porper/models/group.py
porper/models/invited_user.py
porper/models/permission.py
porper/models/resource.py
porper/models/user.py
porper/models/user_group.py
porper-0.3.0.dist-info/DESCRIPTION.rst
porper-0.3.0.dist-info/METADATA
porper-0.3.0.dist-info/RECORD
porper-0.3.0.dist-info/WHEEL
porper-0.3.0.dist-info/metadata.json
porper-0.3.0.dist-info/top_level.txt
