Metadata-Version: 2.0
Name: porper
Version: 0.3.0
Summary: Portable Permission Controller
Home-page: https://github.com/AlexOugh/porper-core
Author: Alex Ough
Author-email: alex.ough@sungardas.com
License: Free for non-commercial use
Keywords: serverless lambda permission
Platform: UNKNOWN
Classifier: Development Status :: 3 - Alpha
Classifier: Intended Audience :: Developers
Classifier: Topic :: Software Development :: Libraries :: Python Modules
Classifier: License :: Free for non-commercial use
Classifier: Programming Language :: Python :: 2
Classifier: Programming Language :: Python :: 2.6
Classifier: Programming Language :: Python :: 2.7
Requires-Dist: boto3
Requires-Dist: requests
